fortress_alchemy/__init__.py
fortress_alchemy/fortress.py
fortress_alchemy-0.1.0.dist-info/LICENSE
fortress_alchemy-0.1.0.dist-info/METADATA
fortress_alchemy-0.1.0.dist-info/WHEEL
fortress_alchemy-0.1.0.dist-info/RECORD
