Metadata-Version: 2.1
Name: fortress_alchemy
Version: 0.1.0
Summary: Sqlalchemy ORM for Fortress
Author: Fortress
Author-email: founders@fortress.build
Requires-Python: >=3.11,<4.0
Classifier: Programming Language :: Python :: 3
Classifier: Programming Language :: Python :: 3.11
Classifier: Programming Language :: Python :: 3.12
Requires-Dist: fortress-sdk-python (>=0.1.9,<0.2.0)
Requires-Dist: sqlalchemy (>=2.0.32,<3.0.0)
